harbinger_vault_client/__init__.py
harbinger_vault_client/cliente.py
harbinger_vault_client-0.2.0.dist-info/licenses/LICENSE
harbinger_vault_client-0.2.0.dist-info/METADATA
harbinger_vault_client-0.2.0.dist-info/WHEEL
harbinger_vault_client-0.2.0.dist-info/top_level.txt
harbinger_vault_client-0.2.0.dist-info/RECORD
